{
  "openapi": "3.0.0",
  "info": {
    "title": "Movies API",
    "version": "1.0.0",
    "description": "API documentation for Movies and Categories collections"
  },
  "servers": [
    {
      "url": "https://movies-api-gu0u.onrender.com"
    }
  ],

  "components": {
    "securitySchemes": {
      "OAuth2Password": {
        "type": "oauth2",
        "flows": {
          "password": {
            "tokenUrl": "/auth/login",
            "scopes": {}
          }
        }
      }
    },

    "schemas": {
      "Movie": {
        "type": "object",
        "properties": {
          "title": { "type": "string" },
          "director": { "type": "string" },
          "year": { "type": "integer" },
          "genre": { "type": "string" },
          "rating": { "type": "number" },
          "duration": { "type": "integer" },
          "description": { "type": "string" },
          "category": {
            "type": "string",
            "description": "Category ID"
          }
        },
        "required": [
          "title",
          "director",
          "year",
          "genre",
          "rating",
          "duration",
          "description",
          "category"
        ]
      },

      "Category": {
        "type": "object",
        "properties": {
          "name": { "type": "string" }
        },
        "required": ["name"]
      }
    }
  },

  "paths": {
    "/movies": {
      "get": {
        "summary": "Get all movies",
        "responses": {
          "200": { "description": "List of movies" }
        }
      },
      "post": {
        "summary": "Create a new movie",
        "security": [{ "OAuth2Password": [] }],
        "requestBody": {
          "required": true,
          "content": {
            "application/json": {
              "schema": {
                "$ref": "#/components/schemas/Movie"
              }
            }
          }
        },
        "responses": {
          "201": { "description": "Movie created successfully" },
          "400": { "description": "Invalid input" },
          "404": { "description": "Category not found" },
          "401": { "description": "Unauthorized" }
        }
      }
    },

    "/movies/{id}": {
      "get": {
        "summary": "Get a movie by ID",
        "parameters": [
          {
            "name": "id",
            "in": "path",
            "required": true,
            "schema": { "type": "string" }
          }
        ],
        "responses": {
          "200": { "description": "Movie found" },
          "400": { "description": "Invalid ID" },
          "404": { "description": "Movie not found" }
        }
      },
      "put": {
        "summary": "Update a movie by ID",
        "security": [{ "OAuth2Password": [] }],
        "parameters": [
          {
            "name": "id",
            "in": "path",
            "required": true,
            "schema": { "type": "string" }
          }
        ],
        "requestBody": {
          "required": true,
          "content": {
            "application/json": {
              "schema": { "$ref": "#/components/schemas/Movie" }
            }
          }
        },
        "responses": {
          "200": { "description": "Movie updated" },
          "400": { "description": "Invalid input" },
          "404": { "description": "Movie not found" },
          "401": { "description": "Unauthorized" }
        }
      },
      "delete": {
        "summary": "Delete a movie by ID",
        "security": [{ "OAuth2Password": [] }],
        "parameters": [
          {
            "name": "id",
            "in": "path",
            "required": true,
            "schema": { "type": "string" }
          }
        ],
        "responses": {
          "200": { "description": "Movie deleted" },
          "400": { "description": "Invalid ID" },
          "404": { "description": "Movie not found" },
          "401": { "description": "Unauthorized" }
        }
      }
    },

    "/categories": {
      "get": {
        "summary": "Get all categories",
        "responses": {
          "200": { "description": "List of categories" }
        }
      },
      "post": {
        "summary": "Create a new category",
        "security": [{ "OAuth2Password": [] }],
        "requestBody": {
          "required": true,
          "content": {
            "application/json": {
              "schema": { "$ref": "#/components/schemas/Category" }
            }
          }
        },
        "responses": {
          "201": { "description": "Category created successfully" },
          "400": { "description": "Invalid input" },
          "401": { "description": "Unauthorized" }
        }
      }
    },

    "/categories/{id}": {
      "get": {
        "summary": "Get a category by ID",
        "parameters": [
          {
            "name": "id",
            "in": "path",
            "required": true,
            "schema": { "type": "string" }
          }
        ],
        "responses": {
          "200": { "description": "Category found" },
          "400": { "description": "Invalid ID" },
          "404": { "description": "Category not found" }
        }
      },
      "put": {
        "summary": "Update a category by ID",
        "security": [{ "OAuth2Password": [] }],
        "parameters": [
          {
            "name": "id",
            "in": "path",
            "required": true,
            "schema": { "type": "string" }
          }
        ],
        "requestBody": {
          "required": true,
          "content": {
            "application/json": {
              "schema": { "$ref": "#/components/schemas/Category" }
            }
          }
        },
        "responses": {
          "200": { "description": "Category updated" },
          "400": { "description": "Invalid ID or input" },
          "404": { "description": "Category not found" },
          "401": { "description": "Unauthorized" }
        }
      },
      "delete": {
        "summary": "Delete a category by ID",
        "security": [{ "OAuth2Password": [] }],
        "parameters": [
          {
            "name": "id",
            "in": "path",
            "required": true,
            "schema": { "type": "string" }
          }
        ],
        "responses": {
          "200": { "description": "Category deleted" },
          "400": { "description": "Invalid ID" },
          "404": { "description": "Category not found" },
          "401": { "description": "Unauthorized" }
        }
      }
    }
  }
}
